py2zenodo/__init__.py
py2zenodo/cli.py
py2zenodo/py2zenodo.py
py2zenodo-0.1.0a1.dist-info/entry_points.txt
py2zenodo-0.1.0a1.dist-info/LICENSE
py2zenodo-0.1.0a1.dist-info/WHEEL
py2zenodo-0.1.0a1.dist-info/METADATA
py2zenodo-0.1.0a1.dist-info/RECORD
